authlib/__init__.py
authlib/consts.py
authlib/deprecate.py
authlib/common/__init__.py
authlib/common/encoding.py
authlib/common/errors.py
authlib/common/security.py
authlib/common/urls.py
authlib/integrations/__init__.py
authlib/integrations/django_helpers.py
authlib/integrations/flask_helpers.py
authlib/integrations/base_client/__init__.py
authlib/integrations/base_client/async_app.py
authlib/integrations/base_client/base_app.py
authlib/integrations/base_client/base_oauth.py
authlib/integrations/base_client/errors.py
authlib/integrations/base_client/framework_integration.py
authlib/integrations/base_client/remote_app.py
authlib/integrations/django_client/__init__.py
authlib/integrations/django_client/integration.py
authlib/integrations/django_oauth1/__init__.py
authlib/integrations/django_oauth1/authorization_server.py
authlib/integrations/django_oauth1/nonce.py
authlib/integrations/django_oauth1/resource_protector.py
authlib/integrations/django_oauth2/__init__.py
authlib/integrations/django_oauth2/authorization_server.py
authlib/integrations/django_oauth2/endpoints.py
authlib/integrations/django_oauth2/resource_protector.py
authlib/integrations/django_oauth2/signals.py
authlib/integrations/flask_client/__init__.py
authlib/integrations/flask_client/integration.py
authlib/integrations/flask_client/oauth_registry.py
authlib/integrations/flask_client/remote_app.py
authlib/integrations/flask_oauth1/__init__.py
authlib/integrations/flask_oauth1/authorization_server.py
authlib/integrations/flask_oauth1/cache.py
authlib/integrations/flask_oauth1/resource_protector.py
authlib/integrations/flask_oauth2/__init__.py
authlib/integrations/flask_oauth2/authorization_server.py
authlib/integrations/flask_oauth2/errors.py
authlib/integrations/flask_oauth2/resource_protector.py
authlib/integrations/flask_oauth2/signals.py
authlib/integrations/httpx_client/__init__.py
authlib/integrations/httpx_client/assertion_client.py
authlib/integrations/httpx_client/oauth1_client.py
nevermined_authlib-0.1.0.dist-info/LICENSE
nevermined_authlib-0.1.0.dist-info/METADATA
nevermined_authlib-0.1.0.dist-info/WHEEL
nevermined_authlib-0.1.0.dist-info/top_level.txt
nevermined_authlib-0.1.0.dist-info/RECORD
